README.md
setup.py
diselect/__init__.py
diselect/exceptions.py
diselect/rowset.py
diselect/select.py
diselect.egg-info/PKG-INFO
diselect.egg-info/SOURCES.txt
diselect.egg-info/dependency_links.txt
diselect.egg-info/top_level.txt
diselect/flatten/__init__.py
diselect/flatten/item.py
diselect/queryset/__init__.py
diselect/queryset/normalize.py
diselect/queryset/query.py
diselect/utils/__init__.py
diselect/utils/bases.py
diselect/utils/shortcuts.py