Metadata-Version: 2.1
Name: diselect
Version: 1.0.11
Summary: smart and convenient dict flatten library for complex container nested with dict and list
Home-page: https://github.com/zwolf21/diselect
Author: HS Moon
Author-email: pbr112@naver.com
License: MIT
Keywords: diselect,dict select,flatten,dict flatten,dict in list,list of dict
Platform: UNKNOWN
Classifier: Programming Language :: Python :: 3.8
Classifier: Programming Language :: Python :: 3.9
Classifier: Programming Language :: Python :: 3.10
Requires-Python: >=3.8
